<DOC>Περιορισμός στις αυξήσεις τιμολογίων των <ENAMEX TYPE='ORGANIZATION'>ΔΕΚΟ</ENAMEX>


Ρεπορτάζ: <ENAMEX TYPE='PERSON'>Γ. Διαμαντόπουλος</ENAMEX> 

Η ΑΠΟΦΥΓΗ, όπου είναι δυνατόν, αναπροσαρμογής των τιμολογίων των δημοσίων 
επιχειρήσεων και οργανισμών φαίνεται να αποτελεί βασική κυβερνητική επιλογή, 
προκειμένου να καταστεί δυνατή η περαιτέρω αποκλιμάκωση του πληθωρισμού. 

Το κλίμα αυτό επικρατεί στο <ENAMEX TYPE='ORGANIZATION'>υπουργείο Εθνικής Οικονομίας</ENAMEX>, στέλεχος του οποίου 
τόνιζε χθες ότι η δυσμενής εξέλιξη του τιμάριθμου τον <TIMEX TYPE='DATE'>Ιούνιο</TIMEX> δεν πρέπει να 
προκαλεί υπερβολικές αντιδράσεις. Σύμφωνα με το ίδιο στέλεχος, η αποφυγή 
αναπροσαρμογής των τιμολογίων των <ENAMEX TYPE='ORGANIZATION'>ΔΕΚΟ</ENAMEX> και ο καλύτερος έλεγχος της αγοράς 
είναι οι βασικές προτεραιότητες της κυβέρνησης στην προσπάθεια επανόδου του 
πληθωρισμού σε καθοδική πορεία. 

Οσον αφορά τα τιμολόγια των δημοσίων επιχειρήσεων και οργανισμών, φαίνεται να 
"παγώνουν" τα τέλη της <ENAMEX TYPE='ORGANIZATION'>ΕΥΔΑΠ</ENAMEX>, ενώ ειδικότερα για τα τιμολόγια της <ENAMEX TYPE='ORGANIZATION'>ΔΕΗ</ENAMEX> θα 
εξετασθεί το ενδεχόμενο μιας μικρής αναπροσαρμογής από τον <TIMEX TYPE='DATE'>Σεπτέμβριο</TIMEX>. 

Για τα τιμολόγια του <ENAMEX TYPE='ORGANIZATION'>ΟΤΕ</ENAMEX> μάλλον δεν τίθεται θέμα "παγώματος", αφού οι 
αναπροσαρμογές προβλέπονται από το νόμο μετατροπής του <ENAMEX TYPE='ORGANIZATION'>ΟΤΕ</ENAMEX> σε Α.Ε., με βάση 
τον οποίο έγινε η μετοχοποίησή του.</DOC>

