<DOC><ENAMEX TYPE='LOCATION'>ΙΝΔΟΝΗΣΙΑ</ENAMEX>

Νέα εστία των σεισμών στην <ENAMEX TYPE='LOCATION'>Ασία</ENAMEX>

ΤΟ ΑΜΕΡΙΚΑΝΙΚΟ νόμισμα ενισχύθηκε, χθες, απέναντι στο γιεν, όταν οι φόβοι, 
πως οι κεντρικές τράπεζες θα στηρίξουν το ιαπωνικό νόμισμα, υποχώρησαν, ενώ 
ταυτόχρονα επικράτησε η πεποίθηση, ότι, προς το παρόν τουλάχιστον, τα επιτόκια 
θα παραμείνουν σταθερά. Στα περισσότερα ευρωπαϊκά χρηματιστήρια οι μετοχές 
έπεσαν, καθώς ο δείκτης Dow Jones στη <ENAMEX TYPE='LOCATION'>Νέα Υόρκη</ENAMEX> υποχωρούσε σταθερά. Οι 
ασιατικές αγορές κατρακύλησαν πάλι. Μόνο που το προβάδισμα χθες είχε η 
<ENAMEX TYPE='LOCATION'>Ινδονησία</ENAMEX>, όπου οι μετοχές υποχώρησαν κατά 18,5% μέσα σε μια ατμόσφαιρα στην 
οποία κυριαρχούσαν οι φήμες, ότι ο πρόεδρος <ENAMEX TYPE='PERSON'>Σουχάρτο</ENAMEX> δεν θα επιδιώξει την 
επανεκλογή του τον <TIMEX TYPE='DATE'>Μάρτιο</TIMEX>.

Η κατάρρευση των αγορών στην <ENAMEX TYPE='LOCATION'>Ινδονησία</ENAMEX> συμπαρέσυρε και άλλες ασιατικές 
αγορές. Αν και αξιωματούχοι σε όλο τον κόσμο υπογραμμίζουν ότι οι ανησυχίες, 
πως η χρηματοπιστωτική αναστάτωση στις ασιατικές αγορές θα οδηγήσει σε ευρεία 
ύφεση και σε σημαντική μείωση του ΑΕΠ το <TIMEX TYPE='DATE'>1998</TIMEX>, είναι αβάσιμες, προς στιγμήν 
εντούτοις, οι ενδιαφερόμενοι επενδυτές έχουν "κολλήσει" σε αυτές τις προβλέψεις.

Τα δυσάρεστα νέα από τις ασιατικές αγορές, οι οποίες για μια ακόμα φορά 
υποχώρησαν αισθητά προκαλώντας σύγχυση στους επενδυτές, δεν άφησαν 
ανεπηρέαστη και τη <ENAMEX TYPE='LOCATION'>Νέα Υόρκη</ENAMEX>, καθώς ο δείκτης τιμών Dow Jones έκλεισε με 
απώλειες 1,26% στις 7.802,62 μονάδες.</DOC>

